LICENSE.txt
MANIFEST.in
README.md
setup.cfg
setup.py
color/src/color/color.body.hpp
color/src/color/color.hpp
color/src/color/color.pp2f.hpp
color/src/color/copyright.hpp
color/src/color/LabCH/LabCH.hpp
color/src/color/LabCH/category.hpp
color/src/color/LabCH/akin/LabCH.hpp
color/src/color/LabCH/akin/LuvCH.hpp
color/src/color/LabCH/akin/YCgCo.hpp
color/src/color/LabCH/akin/YDbDr.hpp
color/src/color/LabCH/akin/YPbPr.hpp
color/src/color/LabCH/akin/akin.hpp
color/src/color/LabCH/akin/cmy.hpp
color/src/color/LabCH/akin/cmyk.hpp
color/src/color/LabCH/akin/gray.hpp
color/src/color/LabCH/akin/hsi.hpp
color/src/color/LabCH/akin/hsl.hpp
color/src/color/LabCH/akin/hsv.hpp
color/src/color/LabCH/akin/hwb.hpp
color/src/color/LabCH/akin/lab.hpp
color/src/color/LabCH/akin/lms.hpp
color/src/color/LabCH/akin/luv.hpp
color/src/color/LabCH/akin/rgb.hpp
color/src/color/LabCH/akin/xyy.hpp
color/src/color/LabCH/akin/xyz.hpp
color/src/color/LabCH/akin/yiq.hpp
color/src/color/LabCH/akin/yuv.hpp
color/src/color/LabCH/check/check.hpp
color/src/color/LabCH/check/integrity.hpp
color/src/color/LabCH/check/unique.hpp
color/src/color/LabCH/convert/LabCH.hpp
color/src/color/LabCH/convert/LuvCH.hpp
color/src/color/LabCH/convert/YCgCo.hpp
color/src/color/LabCH/convert/YDbDr.hpp
color/src/color/LabCH/convert/YPbPr.hpp
color/src/color/LabCH/convert/cmy.hpp
color/src/color/LabCH/convert/cmyk.hpp
color/src/color/LabCH/convert/convert.hpp
color/src/color/LabCH/convert/gray.hpp
color/src/color/LabCH/convert/hsi.hpp
color/src/color/LabCH/convert/hsl.hpp
color/src/color/LabCH/convert/hsv.hpp
color/src/color/LabCH/convert/hwb.hpp
color/src/color/LabCH/convert/lab.hpp
color/src/color/LabCH/convert/lms.hpp
color/src/color/LabCH/convert/luv.hpp
color/src/color/LabCH/convert/rgb.hpp
color/src/color/LabCH/convert/xyy.hpp
color/src/color/LabCH/convert/xyz.hpp
color/src/color/LabCH/convert/yiq.hpp
color/src/color/LabCH/convert/yuv.hpp
color/src/color/LabCH/fix/fix.hpp
color/src/color/LabCH/fix/integrity.hpp
piechartocr.egg-info/PKG-INFO
piechartocr.egg-info/SOURCES.txt
piechartocr.egg-info/dependency_links.txt
piechartocr.egg-info/requires.txt
piechartocr.egg-info/top_level.txt
